setup.cfg
setup.py
PBD_Gaussian_Binomial.egg-info/PKG-INFO
PBD_Gaussian_Binomial.egg-info/SOURCES.txt
PBD_Gaussian_Binomial.egg-info/dependency_links.txt
PBD_Gaussian_Binomial.egg-info/not-zip-safe
PBD_Gaussian_Binomial.egg-info/top_level.txt
distributions/Binomialdistribution.py
distributions/Gaussiandistribution.py
distributions/Generaldistribution.py
distributions/__init__.py