Metadata-Version: 1.0
Name: PBD-Gaussian-Binomial
Version: 0.1
Summary: Gaussian and Binomial Distributions
Home-page: UNKNOWN
Author: Andrew Paster
Author-email: UNKNOWN
License: UNKNOWN
Platform: UNKNOWN
